webdb/__init__.py
webdb/adapter/__init__.py
webdb/adapter/abc.py
webdb/adapter/abstractsql.py
webdb/adapter/exceptions.py
webdb/adapter/sqlite.py
webdb/files/__init__.py
webdb/files/dispatcher.py
webdb/files/file.py
webdb/interface/__init__.py
webdb/interface/db.py
webdb/interface/db_interface.py
webdb/interface/file.py
webdb/typehandling/__init__.py
webdb/typehandling/date_and_time.py
webdb/typehandling/typehandling.py
webdb-0.0.1.dist-info/DESCRIPTION.rst
webdb-0.0.1.dist-info/METADATA
webdb-0.0.1.dist-info/RECORD
webdb-0.0.1.dist-info/WHEEL
webdb-0.0.1.dist-info/metadata.json
webdb-0.0.1.dist-info/top_level.txt
