Metadata-Version: 2.0
Name: webdb
Version: 0.0.1
Summary: Adapter for exposing databases to the web
Home-page: https://github.com/daknuett/webdb
Author: Daniel Knüttel
Author-email: daniel.knuettel@daknuett.eu
License: AGPL v3
Keywords: database web json
Platform: UNKNOWN
Classifier: Development Status :: 4 - Beta
Classifier: Intended Audience :: Developers
Classifier: License :: OSI Approved :: GNU Affero General Public License v3
Classifier: Programming Language :: Python :: 3
Requires-Dist: cherrypy
